<?xml version="1.0" encoding="windows-1251"?>
<string_table>
  <!-- Pistols and MP's -->
  <string id="st_mag_sr1m_9x21">
    <text>Стандартный магазин 9x21 СР1М</text>
  </string>

  <string id="st_mag_sr1m_9x21_descr">
    <text>Стандартный магазин 9x21 СР1М ёмкостью на 18 патронов.</text>
  </string>

  <string id="st_mag_sr1m_9x21ext">
    <text>Увеличенный магазин 9x21 СР1М</text>
  </string>

  <string id="st_mag_sr1m_9x21ext_descr">
    <text>Увеличенный магазин 9x21 СР1М ёмкостью на 26 патронов.</text>
  </string>

  <string id="st_mag_pl15_9x19_fmj">
    <text>Стандартный магазин 9x19 ПЛ-15</text>
  </string>

  <string id="st_mag_pl15_9x19_fmj_descr">
    <text>Стандартный магазин 9x19 ПЛ-15 ёмкостью на 16 патронов.</text>
  </string>

  <string id="st_mag_pl15_9x19_fmjext">
    <text>Увеличенный магазин 9x19 ПЛ-15</text>
  </string>

  <string id="st_mag_pl15_9x19_fmjext_descr">
    <text>Стандартный магазин 9x19 ПЛ-15 ёмкостью на 24 патрона.</text>
  </string>

  <string id="st_mag_sigp220_11.43x23_fmj">
    <text>Стандартный магазин .45 SigP220</text>
  </string>

  <string id="st_mag_sigp220_11.43x23_fmj_descr">
    <text>Стандартный магазин .45 SigP220 ёмкостью на 12 патронов.</text>
  </string>

  <string id="st_mag_sigp220_11.43x23_fmjext">
    <text>Увеличенный магазин .45 SigP220</text>
  </string>

  <string id="st_mag_sigp220_11.43x23_fmjext_descr">
    <text>Увеличенный магазин .45 SigP220 ёмкостью на 20 патронов.</text>
  </string>

  <string id="st_mag_sig226_9x19_fmj">
    <text>Стандартный магазин 9x19 SigP226</text>
  </string>

  <string id="st_mag_sig226_9x19_fmj_descr">
    <text>Стандартный магазин 9x19 SigP226 ёмкостью на 15 патронов.</text>
  </string>

  <string id="st_mag_sig226_9x19_fmjext">
    <text>Увеличенный магазин 9x19 SigP226</text>
  </string>

  <string id="st_mag_sig226_9x19_fmjext_descr">
    <text>Увеличенный магазин 9x19 SigP226 ёмкостью на 20 патронов.</text>
  </string>

  <string id="st_mag_usptac_9x19_fmj">
    <text>Стандартный магазин 9x19 USP</text>
  </string>

  <string id="st_mag_usptac_9x19_fmj_descr">
    <text>Стандартный магазин 9x19 USP ёмкостью на 22 патрона.</text>
  </string>

  <string id="st_mag_usptac_9x19_fmjext">
    <text>Увеличенный магазин 9x19 USP</text>
  </string>

  <string id="st_mag_usptac_9x19_fmjext_descr">
    <text>Увеличенный магазин 9x19 USP ёмкостью на 30 патронов.</text>
  </string>

  <string id="st_mag_wp99_9x19_fmj">
    <text>Стандартный магазин 9x19 Walther P99</text>
  </string>

  <string id="st_mag_wp99_9x19_fmj_descr">
    <text>Стандартный магазин 9x19 Walther P99 ёмкостью на 16 патронов.</text>
  </string>

  <string id="st_mag_wp99_9x19_fmjext">
    <text>Увеличенный магазин 9x19 Walther P99</text>
  </string>

  <string id="st_mag_wp99_9x19_fmjext_descr">
    <text>Увеличенный магазин 9x19 Walther P99 ёмкостью на 24 патрона.</text>
  </string>

  <string id="st_mag_p220_9x19_u2p2bas">
    <text>Стандартный магазин 9x19 P220 "9" модернизированный</text>
  </string>

  <string id="st_mag_p220_9x19_u2p2bas_descr">
    <text>Стандартный магазин 9x19 P220 "9" модернизированный ёмкостью на 19 патронов.</text>
  </string>
</string_table>
