<?xml version="1.0" encoding="windows-1251"?>

<!--
	BaS Weapons
-->

<string_table>
	
	
	
	<string id="st_wpn_sks_b">
		<text>СКС</text>
	</string>
	<string id="st_wpn_sks_b_descr">
		<text>Советский самозарядный карабин конструкции Сергея Симонова принят на вооружение в 1949 году. Заменённый в начале 1950-х годов на переднем крае войсковой службы автоматом АК, он остался в запасе на десятилетия и до сих пор используется в качестве парадно-церемониального оружия.\n \n
		%c[ui_gray_2]НАВЕСНОЕ ОБОРУДОВАНИЕ: \n%c[d_purple]• %c[ui_gray_2] Прицел ПУ\n</text>
	</string>

	
	
</string_table>
